{
  "project_info": {
    "project_number": "213592688170",
    "project_id": "ultra-store-86c05",
    "storage_bucket": "ultra-store-86c05.appspot.com"
  },
  "client": [
    {
      "client_info": {
        "mobilesdk_app_id": "1:213592688170:android:0014413b30b33eb024a553",
        "android_client_info": {
          "package_name": "com.example.full_ecommerce_app"
        }
      },
      "oauth_client": [],
      "api_key": [
        {
          "current_key": "AIzaSyBAz5OXsFADMdU-G_rD4_PENdLIYv0i7pU"
        }
      ],
      "services": {
        "appinvite_service": {
          "other_platform_oauth_client": []
        }
      }
    }
  ],
  "configuration_version": "1"
}